vprikol_api/__init__.py
vprikol_api/api.py
vprikol_api/main.py
vprikol_api/model.py
vprikol_api_python-1.12.dist-info/METADATA
vprikol_api_python-1.12.dist-info/WHEEL
vprikol_api_python-1.12.dist-info/RECORD
