Metadata-Version: 2.1
Name: vprikol-api-python
Version: 1.12
Summary: 
Author: Alex
Author-email: alexank1111@gmail.com
Requires-Python: >=3.10,<4.0
Classifier: Programming Language :: Python :: 3
Classifier: Programming Language :: Python :: 3.10
Classifier: Programming Language :: Python :: 3.11
Classifier: Programming Language :: Python :: 3.12
Requires-Dist: aiohttp (>=3.8.4,<4.0.0)
Requires-Dist: pydantic (>=1.10.7,<2.0.0)
